setup.py
function_profiler.egg-info/PKG-INFO
function_profiler.egg-info/SOURCES.txt
function_profiler.egg-info/dependency_links.txt
function_profiler.egg-info/requires.txt
function_profiler.egg-info/top_level.txt
profiler/__init__.py
profiler/profiler.py