Metadata-Version: 1.1
Name: function-profiler
Version: 1.0
Summary: A Python decorator to profile function performance.
Home-page: https://github.com/Datamine/Function-Profiler
Author: John Loeber
Author-email: contact@johnloeber.com
License: MIT
Platform: UNKNOWN
Classifier: Development Status :: 3 - Alpha
Classifier: Programming Language :: Python :: 3.6
